{
  "name": "Galician Tradition Tree",
  "length": 0.0,
  "children": [
    {
      "name": "pasacorredoiras",
      "length": 169.55658626018402,
      "display_name": "pasacorredoiras"
    },
    {
      "name": "",
      "length": 169.55658626018402,
      "children": [
        {
          "name": "",
          "length": 0.29099843212898513,
          "children": [
            {
              "name": "",
              "length": 1.2174132829899236,
              "children": [
                {
                  "name": "rumbas",
                  "length": 350.70993894829684,
                  "display_name": "rumbas"
                },
                {
                  "name": "valses",
                  "length": 476.5983672440728,
                  "display_name": "valses"
                }
              ],
              "tradition": "galician"
            },
            {
              "name": "",
              "length": 0.39940388243951475,
              "children": [
                {
                  "name": "",
                  "length": 0.8252682501910783,
                  "children": [
                    {
                      "name": "pasodobles",
                      "length": 396.18056088336,
                      "display_name": "pasodobles"
                    },
                    {
                      "name": "",
                      "length": 1.1806050700577657,
                      "children": [
                        {
                          "name": "mazurcas",
                          "length": 375.31513058183884,
                          "display_name": "mazurcas"
                        },
                        {
                          "name": "",
                          "length": 3.465294761941152,
                          "children": [
                            {
                              "name": "foliadas",
                              "length": 417.4133484512336,
                              "display_name": "foliadas"
                            },
                            {
                              "name": "jotas",
                              "length": 484.97439022644045,
                              "display_name": "jotas"
                            }
                          ],
                          "tradition": "galician"
                        }
                      ],
                      "tradition": "galician"
                    }
                  ],
                  "tradition": "galician"
                },
                {
                  "name": "marchas",
                  "length": 375.28670012135944,
                  "display_name": "marchas",
                  "tradition": "galician"
                }
              ],
              "tradition": "galician"
            }
          ],
          "tradition": "galician"
        },
        {
          "name": "",
          "length": 0.18047039139915277,
          "children": [
            {
              "name": "alalas",
              "length": 188.5637985916558,
              "display_name": "alalas",
              "tradition": "galician"
            },
            {
              "name": "",
              "length": 0.2856728991489348,
              "children": [
                {
                  "name": "polca",
                  "length": 324.0987994642461,
                  "display_name": "polca"
                },
                {
                  "name": "muineiras",
                  "length": 357.90010158703626,
                  "display_name": "muineiras"
                }
              ],
              "tradition": "galician"
            }
          ],
          "tradition": "galician"
        }
      ],
      "tradition": "galician"
    }
  ],
  "tradition": "galician"
}